fake_ssh/__init__.py
fake_ssh/command.py
fake_ssh/connection_handler.py
fake_ssh/demo/__init__.py
fake_ssh/demo/echo_server.py
fake_ssh/server.py
fake_ssh/server_key
fake_ssh/utils.py
fake_ssh-0.1.0a5.dist-info/entry_points.txt
fake_ssh-0.1.0a5.dist-info/WHEEL
fake_ssh-0.1.0a5.dist-info/METADATA
fake_ssh-0.1.0a5.dist-info/RECORD
