Metadata-Version: 2.1
Name: fake-ssh
Version: 0.1.0a5
Summary: Fakes an SSH Server
Home-page: https://github.com/d1618033/fake-ssh.git
License: MIT
Keywords: SSH,Server,Mocking,Mock,Testing
Author: David Sternlicht
Author-email: dsternlicht@infinidat.com
Requires-Python: >=3.7,<4.0
Classifier: License :: OSI Approved :: MIT License
Classifier: Programming Language :: Python :: 3
Classifier: Programming Language :: Python :: 3.7
Classifier: Programming Language :: Python :: 3.8
Classifier: Programming Language :: Python :: 3.9
Requires-Dist: Logbook (>=1.5.3,<2.0.0)
Requires-Dist: paramiko (>=2.4,<3.0)
Project-URL: Repository, https://github.com/d1618033/fake-ssh.git
